jupyter_io/__init__.py
jupyter_io/io.py
jupyter_io/py.typed
jupyter_io/v0.py
jupyter_io-2.0.1.dist-info/METADATA
jupyter_io-2.0.1.dist-info/WHEEL
jupyter_io-2.0.1.dist-info/licenses/LICENSE
jupyter_io-2.0.1.dist-info/RECORD
