Metadata-Version: 2.4
Name: jupyter-io
Version: 2.0.1
Summary: Saving and loading files directly into Jupyter notebooks
Project-URL: homepage, https://astropenguin.github.io/jupyter-io/v2.0.1
Project-URL: repository, https://github.com/astropenguin/jupyter-io
Author-email: Akio Taniguchi <taniguchi.akio@gmail.com>
License: MIT License
License-File: LICENSE
Keywords: io,jupyter,python
Classifier: License :: OSI Approved :: MIT License
Classifier: Programming Language :: Python :: 3
Classifier: Programming Language :: Python :: 3.9
Classifier: Programming Language :: Python :: 3.10
Classifier: Programming Language :: Python :: 3.11
Classifier: Programming Language :: Python :: 3.12
Classifier: Programming Language :: Python :: 3.13
Requires-Python: <3.14,>=3.9
Requires-Dist: ipython<9.0,>=7.0
Requires-Dist: matplotlib<4.0,>=3.0
Requires-Dist: pandas-stubs<3.0,>=1.5
Requires-Dist: pandas<3.0,>=1.5
